crud_mysql/__init__.py
crud_mysql/crud_object.py
crud_mysql/endpoints.py
crud_mysql/vars.py
crud_mysql-0.1.5.dist-info/licenses/LICENCE
crud_mysql-0.1.5.dist-info/METADATA
crud_mysql-0.1.5.dist-info/WHEEL
crud_mysql-0.1.5.dist-info/top_level.txt
crud_mysql-0.1.5.dist-info/RECORD
