Metadata-Version: 2.4
Name: crud-mysql
Version: 0.1.5
Summary: crud defiend by json
Home-page: https://github.com/Ms-Shoshany/crud-mysql
Author: hanna
Author-email: channashosh@gmail.com
Classifier: Programming Language :: Python :: 3
Classifier: License :: OSI Approved :: MIT License
Classifier: Operating System :: OS Independent
Requires-Python: >=3.7
License-File: LICENCE
Requires-Dist: mysql-connector-python
Requires-Dist: mysql-database
Requires-Dist: flask
Dynamic: author
Dynamic: author-email
Dynamic: classifier
Dynamic: description
Dynamic: description-content-type
Dynamic: home-page
Dynamic: license-file
Dynamic: requires-dist
Dynamic: requires-python
Dynamic: summary
